{
    "debug_notice": {
        "en": "This tool is running in debug mode.",
        "fr": "Cet outil est en mode debug."
    },
    "capability_label": {
        "en": "Capability",
        "fr": "Capacité"
    },
    "group_CA": {
        "en": "Army",
        "fr": "Armée"
    },
    "group_RCAF": {
        "en": "Royal Canadian Air Force",
        "fr": "Aviation royale canadienne"
    },
    "group_Joint": {
        "en": "Joint",
        "fr": "Interarmées"
    },
    "group_RCN": {
        "en": "Royal Canadian Navy",
        "fr": "Marine royale canadienne"
    },
    "impact_per_unit_toggle": {
        "en": "Per step",
        "fr": "Par étape"
    },
    "impact_cost_title": {
        "en": "Cost Impact",
        "fr": "Impact sur les coûts"
    },
    "impact_personnel_title": {
        "en": "Personnel Impact",
        "fr": "Impact sur le personnel"
    },
    "impact_facet_label_direct": {
        "en": "Direct",
        "fr": "Direct"
    },
    "impact_facet_label_indirect": {
        "en": "Indirect",
        "fr": "Indirect"
    },
    "impact_facet_label_env_overhead": {
        "en": "Env. Overhead",
        "fr": "Surcharge environement"
    },
    "impact_facet_label_inst_overhead": {
        "en": "Inst. Overhead",
        "fr": "???? Inst Overhead"
    },
    "impact_facet_label_total": {
        "en": "Total",
        "fr": "Total"
    },
    "summary_title": {
        "en": "Summary",
        "fr": "Sommaire"
    },
    "chart_alt_text_label": {
        "en": "Text version",
        "fr": "Version textuelle"
    }
}